{
  "_meta": {
    "generated": "2026-04-26T15:45:57.939Z",
    "source": "_ml_dataset_v6_final_comprehensive.json",
    "total_slugs": 150,
    "total_recipes": 1100,
    "main_categories": 14
  },
  "categories": {
    "Belgian Strong / Trappist": {
      "n_slugs": 4,
      "n_recipes": 68,
      "slugs": [
        {
          "slug": "belgian_dubbel",
          "n": 26
        },
        {
          "slug": "belgian_tripel",
          "n": 18
        },
        {
          "slug": "belgian_strong_dark_ale",
          "n": 15
        },
        {
          "slug": "belgian_quadrupel",
          "n": 9
        }
      ]
    },
    "Belgian Pale / Witbier": {
      "n_slugs": 5,
      "n_recipes": 48,
      "slugs": [
        {
          "slug": "belgian_blonde_ale",
          "n": 16
        },
        {
          "slug": "belgian_witbier",
          "n": 15
        },
        {
          "slug": "belgian_session_ale",
          "n": 5
        },
        {
          "slug": "other_belgian_ale",
          "n": 2
        },
        {
          "slug": "ipa",
          "n": 10
        }
      ]
    },
    "Saison / Farmhouse": {
      "n_slugs": 4,
      "n_recipes": 59,
      "slugs": [
        {
          "slug": "french_belgian_saison",
          "n": 41
        },
        {
          "slug": "specialty_saison",
          "n": 7
        },
        {
          "slug": "french_biere_de_garde",
          "n": 8
        },
        {
          "slug": "finnish_sahti",
          "n": 3
        }
      ]
    },
    "Sour / Wild / Brett": {
      "n_slugs": 12,
      "n_recipes": 105,
      "slugs": [
        {
          "slug": "flanders_red_ale",
          "n": 16
        },
        {
          "slug": "belgian_fruit_lambic",
          "n": 16
        },
        {
          "slug": "gueuze",
          "n": 11
        },
        {
          "slug": "gose",
          "n": 13
        },
        {
          "slug": "berliner_weisse",
          "n": 7
        },
        {
          "slug": "oud_bruin",
          "n": 5
        },
        {
          "slug": "american_wild_ale",
          "n": 18
        },
        {
          "slug": "brett_beer",
          "n": 6
        },
        {
          "slug": "belgian_lambic",
          "n": 4
        },
        {
          "slug": "american_fruited_sour_ale",
          "n": 4
        },
        {
          "slug": "mixed_fermentation_sour_beer",
          "n": 2
        },
        {
          "slug": "lichtenhainer",
          "n": 3
        }
      ]
    },
    "German Lager": {
      "n_slugs": 26,
      "n_recipes": 181,
      "slugs": [
        {
          "slug": "pale_lager",
          "n": 35
        },
        {
          "slug": "munich_helles",
          "n": 14
        },
        {
          "slug": "festbier",
          "n": 13
        },
        {
          "slug": "german_maerzen",
          "n": 12
        },
        {
          "slug": "german_doppelbock",
          "n": 12
        },
        {
          "slug": "german_pilsener",
          "n": 12
        },
        {
          "slug": "german_schwarzbier",
          "n": 11
        },
        {
          "slug": "vienna_lager",
          "n": 11
        },
        {
          "slug": "dark_lager",
          "n": 8
        },
        {
          "slug": "kellerbier",
          "n": 6
        },
        {
          "slug": "dortmunder_european_export",
          "n": 6
        },
        {
          "slug": "bamberg_maerzen_rauchbier",
          "n": 5
        },
        {
          "slug": "munich_dunkel",
          "n": 5
        },
        {
          "slug": "bamberg_bock_rauchbier",
          "n": 3
        },
        {
          "slug": "german_heller_bock_maibock",
          "n": 2
        },
        {
          "slug": "bamberg_helles_rauchbier",
          "n": 2
        },
        {
          "slug": "german_leichtbier",
          "n": 1
        },
        {
          "slug": "franconian_rotbier",
          "n": 1
        },
        {
          "slug": "dunkles_bock",
          "n": 1
        },
        {
          "slug": "dortmunder_export",
          "n": 1
        },
        {
          "slug": "czech_amber_lager",
          "n": 2
        },
        {
          "slug": "baltic_porter",
          "n": 8
        },
        {
          "slug": "italian_pilsner",
          "n": 3
        },
        {
          "slug": "new_zealand_pilsner",
          "n": 2
        },
        {
          "slug": "breslau_schoeps",
          "n": 2
        },
        {
          "slug": "helles_bock",
          "n": 3
        }
      ]
    },
    "German Wheat": {
      "n_slugs": 8,
      "n_recipes": 33,
      "slugs": [
        {
          "slug": "south_german_hefeweizen",
          "n": 12
        },
        {
          "slug": "weizenbock",
          "n": 8
        },
        {
          "slug": "south_german_dunkel_weizen",
          "n": 4
        },
        {
          "slug": "south_german_kristal_weizen",
          "n": 2
        },
        {
          "slug": "german_rye_ale",
          "n": 4
        },
        {
          "slug": "south_german_bernsteinfarbenes_weizen",
          "n": 1
        },
        {
          "slug": "dunkles_weissbier",
          "n": 1
        },
        {
          "slug": "german_weissbier",
          "n": 1
        }
      ]
    },
    "Hybrid Ale-Lager": {
      "n_slugs": 12,
      "n_recipes": 73,
      "slugs": [
        {
          "slug": "german_altbier",
          "n": 17
        },
        {
          "slug": "german_koelsch",
          "n": 16
        },
        {
          "slug": "common_beer",
          "n": 8
        },
        {
          "slug": "american_lager",
          "n": 9
        },
        {
          "slug": "cream_ale",
          "n": 3
        },
        {
          "slug": "mexican_amber_lager",
          "n": 5
        },
        {
          "slug": "mexican_pale_lager",
          "n": 4
        },
        {
          "slug": "west_coast_pilsener",
          "n": 3
        },
        {
          "slug": "pre_prohibition_lager",
          "n": 3
        },
        {
          "slug": "rice_lager",
          "n": 3
        },
        {
          "slug": "american_light_lager",
          "n": 1
        },
        {
          "slug": "american_india_pale_lager",
          "n": 1
        }
      ]
    },
    "British Bitter / Mild": {
      "n_slugs": 6,
      "n_recipes": 30,
      "slugs": [
        {
          "slug": "special_bitter_or_best_bitter",
          "n": 8
        },
        {
          "slug": "mild",
          "n": 11
        },
        {
          "slug": "ordinary_bitter",
          "n": 4
        },
        {
          "slug": "extra_special_bitter",
          "n": 3
        },
        {
          "slug": "strong_bitter",
          "n": 2
        },
        {
          "slug": "english_summer_ale",
          "n": 2
        }
      ]
    },
    "British Strong / Old": {
      "n_slugs": 9,
      "n_recipes": 35,
      "slugs": [
        {
          "slug": "british_barley_wine_ale",
          "n": 7
        },
        {
          "slug": "strong_ale",
          "n": 3
        },
        {
          "slug": "old_ale",
          "n": 4
        },
        {
          "slug": "scotch_ale_or_wee_heavy",
          "n": 8
        },
        {
          "slug": "scottish_export",
          "n": 6
        },
        {
          "slug": "strong_scotch_ale",
          "n": 2
        },
        {
          "slug": "scottish_heavy",
          "n": 2
        },
        {
          "slug": "scottish_light",
          "n": 1
        },
        {
          "slug": "eisbock",
          "n": 2
        }
      ]
    },
    "Stout / Porter": {
      "n_slugs": 13,
      "n_recipes": 112,
      "slugs": [
        {
          "slug": "porter",
          "n": 18
        },
        {
          "slug": "american_imperial_stout",
          "n": 29
        },
        {
          "slug": "sweet_stout",
          "n": 13
        },
        {
          "slug": "oatmeal_stout",
          "n": 12
        },
        {
          "slug": "irish_dry_stout",
          "n": 8
        },
        {
          "slug": "stout",
          "n": 11
        },
        {
          "slug": "brown_porter",
          "n": 4
        },
        {
          "slug": "robust_porter",
          "n": 4
        },
        {
          "slug": "british_imperial_stout",
          "n": 5
        },
        {
          "slug": "export_stout",
          "n": 3
        },
        {
          "slug": "smoke_porter",
          "n": 2
        },
        {
          "slug": "tropical_stout",
          "n": 1
        },
        {
          "slug": "foreign_extra_stout",
          "n": 2
        }
      ]
    },
    "Irish / Red Ale": {
      "n_slugs": 3,
      "n_recipes": 43,
      "slugs": [
        {
          "slug": "irish_red_ale",
          "n": 6
        },
        {
          "slug": "american_amber_red_ale",
          "n": 10
        },
        {
          "slug": "brown_ale",
          "n": 27
        }
      ]
    },
    "American Hoppy": {
      "n_slugs": 23,
      "n_recipes": 227,
      "slugs": [
        {
          "slug": "american_india_pale_ale",
          "n": 59
        },
        {
          "slug": "double_ipa",
          "n": 20
        },
        {
          "slug": "pale_ale",
          "n": 33
        },
        {
          "slug": "juicy_or_hazy_india_pale_ale",
          "n": 16
        },
        {
          "slug": "session_india_pale_ale",
          "n": 10
        },
        {
          "slug": "black_ipa",
          "n": 10
        },
        {
          "slug": "white_ipa",
          "n": 8
        },
        {
          "slug": "brut_ipa",
          "n": 8
        },
        {
          "slug": "west_coast_india_pale_ale",
          "n": 7
        },
        {
          "slug": "rye_ipa",
          "n": 4
        },
        {
          "slug": "triple_ipa",
          "n": 2
        },
        {
          "slug": "juicy_or_hazy_strong_pale_ale",
          "n": 2
        },
        {
          "slug": "juicy_or_hazy_double_india_pale_ale",
          "n": 2
        },
        {
          "slug": "british_india_pale_ale",
          "n": 3
        },
        {
          "slug": "blonde_ale",
          "n": 10
        },
        {
          "slug": "american_wheat_ale",
          "n": 7
        },
        {
          "slug": "american_wheat_wine_ale",
          "n": 3
        },
        {
          "slug": "imperial_red_ale",
          "n": 3
        },
        {
          "slug": "red_ipa",
          "n": 1
        },
        {
          "slug": "ipa_dark",
          "n": 1
        },
        {
          "slug": "australian_pale_ale",
          "n": 2
        },
        {
          "slug": "american_barleywine",
          "n": 13
        },
        {
          "slug": "rye_beer",
          "n": 3
        }
      ]
    },
    "Specialty / Adjunct": {
      "n_slugs": 16,
      "n_recipes": 71,
      "slugs": [
        {
          "slug": "fruit_beer",
          "n": 10
        },
        {
          "slug": "dessert_stout_or_pastry_beer",
          "n": 10
        },
        {
          "slug": "winter_seasonal_beer",
          "n": 7
        },
        {
          "slug": "smoked_beer",
          "n": 7
        },
        {
          "slug": "pumpkin_squash_beer",
          "n": 6
        },
        {
          "slug": "pumpkin_spice_beer",
          "n": 5
        },
        {
          "slug": "fruit_wheat_beer",
          "n": 5
        },
        {
          "slug": "coffee_beer",
          "n": 4
        },
        {
          "slug": "chocolate_or_cocoa_beer",
          "n": 4
        },
        {
          "slug": "chili_pepper_beer",
          "n": 4
        },
        {
          "slug": "herb_and_spice_beer",
          "n": 2
        },
        {
          "slug": "spice_herb_or_vegetable_beer",
          "n": 1
        },
        {
          "slug": "autumn_seasonal_beer",
          "n": 1
        },
        {
          "slug": "specialty_honey_beer",
          "n": 1
        },
        {
          "slug": "experimental_beer",
          "n": 3
        },
        {
          "slug": "specialty_beer",
          "n": 1
        }
      ]
    },
    "Historical / Special": {
      "n_slugs": 9,
      "n_recipes": 15,
      "slugs": [
        {
          "slug": "specialty_historical",
          "n": 3
        },
        {
          "slug": "piwo_grodziskie",
          "n": 2
        },
        {
          "slug": "adambier",
          "n": 2
        },
        {
          "slug": "historical_beer",
          "n": 2
        },
        {
          "slug": "swedish_gotlandsdricke",
          "n": 1
        },
        {
          "slug": "dutch_kuit_kuyt_or_koyt",
          "n": 1
        },
        {
          "slug": "gluten_free_beer",
          "n": 2
        },
        {
          "slug": "non_alcohol_malt_beverage",
          "n": 1
        },
        {
          "slug": "french_amber_ale",
          "n": 1
        }
      ]
    }
  }
}