{
  "_meta": {
    "errors": {
      "not_all_grain": 0,
      "no_grain": 0,
      "no_slug": 1,
      "bad_og": 0,
      "bad_fg": 0,
      "bad_srm": 0,
      "no_recipe_data": 1179
    },
    "total": 2
  },
  "records": [
    {
      "id": "brulosophy_short-shoddy-american-ipa",
      "source": "brulosophy",
      "source_id": "/2018/01/18/short-shoddy-american-ipa/",
      "name": "Short   Shoddy",
      "bjcp_slug": "piwo_grodziskie",
      "bjcp_main_category": "Historical / Special",
      "sorte_raw": ", the historical evidence seems to suggest India was actually receiving standard",
      "raw": {
        "malts": [
          {
            "name": "Saaz l",
            "amount_kg": 0.056699
          }
        ],
        "hops": [
          "amarillo",
          "Amarillo",
          "saphir",
          "Saphir",
          "mosaic",
          "Mosaic",
          "target",
          "Galaxy",
          "Citra",
          "Simcoe",
          "Saaz"
        ],
        "yeast": "",
        "og": 1.062,
        "fg": null,
        "abv": null,
        "ibu": null,
        "srm": null
      },
      "features": {
        "og": 1.062,
        "fg": 0,
        "abv": 0,
        "ibu": 0,
        "srm": 0,
        "pct_pilsner": 0,
        "pct_pale_ale": 0,
        "pct_munich": 0,
        "pct_vienna": 0,
        "pct_wheat": 0,
        "pct_oats": 0,
        "pct_rye": 0,
        "pct_crystal": 0,
        "pct_choc": 0,
        "pct_roast": 0,
        "pct_smoked": 0,
        "pct_corn": 0,
        "pct_rice": 0,
        "pct_sugar": 0,
        "pct_aromatic_abbey": 0,
        "pct_sixrow": 0,
        "pct_other": 100,
        "total_base": 0,
        "yeast_belgian": 0,
        "yeast_abbey": 0,
        "yeast_saison": 0,
        "yeast_kveik": 0,
        "yeast_english": 0,
        "yeast_american": 0,
        "yeast_german_lager": 0,
        "yeast_czech_lager": 0,
        "yeast_american_lager": 0,
        "yeast_kolsch": 0,
        "yeast_altbier": 0,
        "yeast_cal_common": 0,
        "yeast_brett": 0,
        "yeast_lacto": 0,
        "yeast_sour_blend": 0,
        "yeast_witbier": 0,
        "yeast_wheat_german": 0,
        "yeast_wit": 0,
        "hop_american_c": 1,
        "hop_english": 1,
        "hop_german": 1,
        "hop_czech_saaz": 1,
        "hop_nz": 0,
        "hop_aged": 0,
        "hop_northern_brewer": 0,
        "katki_fruit": 0,
        "katki_spice_herb": 0,
        "katki_chocolate": 0,
        "katki_coffee": 0,
        "katki_chile": 0,
        "katki_smoke": 0,
        "katki_honey": 0,
        "katki_pumpkin": 0,
        "katki_salt": 0,
        "katki_lactose": 0,
        "mash_temp_c": 66,
        "fermentation_temp_c": 19,
        "yeast_attenuation": 78,
        "boil_time_min": 60,
        "water_ca_ppm": 150,
        "water_so4_ppm": 250,
        "water_cl_ppm": 120,
        "dry_hop_days": 0,
        "mash_type_step": 0,
        "mash_type_decoction": 0,
        "lagering_days": 0
      },
      "in_split": null
    },
    {
      "id": "madferm_wyeast-de-bom-quick-sour",
      "source": "madferm",
      "source_id": "/2016/09/wyeast-de-bom-quick-sour.html",
      "name": "Wyeast De Bom \"Quick\" \"Sour\"",
      "bjcp_slug": "french_belgian_saison",
      "bjcp_main_category": "Saison / Farmhouse",
      "sorte_raw": "Saison in one and Lallemand Belle Saison",
      "raw": {
        "malts": [
          {
            "name": "CaCl was",
            "amount_kg": 0.006
          }
        ],
        "hops": [
          "galaxy",
          "Galaxy",
          "summit",
          "Summit",
          "target"
        ],
        "yeast": "Lallemand Belle Saison",
        "og": 1.053,
        "fg": 1.002,
        "abv": 6.7,
        "ibu": 24.3,
        "srm": 4.2
      },
      "features": {
        "og": 1.053,
        "fg": 1.002,
        "abv": 6.7,
        "ibu": 24.3,
        "srm": 4.2,
        "pct_pilsner": 0,
        "pct_pale_ale": 0,
        "pct_munich": 0,
        "pct_vienna": 0,
        "pct_wheat": 0,
        "pct_oats": 0,
        "pct_rye": 0,
        "pct_crystal": 0,
        "pct_choc": 0,
        "pct_roast": 0,
        "pct_smoked": 0,
        "pct_corn": 0,
        "pct_rice": 0,
        "pct_sugar": 0,
        "pct_aromatic_abbey": 0,
        "pct_sixrow": 0,
        "pct_other": 100,
        "total_base": 0,
        "yeast_belgian": 1,
        "yeast_abbey": 0,
        "yeast_saison": 1,
        "yeast_kveik": 0,
        "yeast_english": 0,
        "yeast_american": 0,
        "yeast_german_lager": 0,
        "yeast_czech_lager": 0,
        "yeast_american_lager": 0,
        "yeast_kolsch": 0,
        "yeast_altbier": 0,
        "yeast_cal_common": 0,
        "yeast_brett": 0,
        "yeast_lacto": 0,
        "yeast_sour_blend": 0,
        "yeast_witbier": 0,
        "yeast_wheat_german": 0,
        "yeast_wit": 0,
        "hop_american_c": 1,
        "hop_english": 1,
        "hop_german": 0,
        "hop_czech_saaz": 0,
        "hop_nz": 0,
        "hop_aged": 0,
        "hop_northern_brewer": 0,
        "katki_fruit": 0,
        "katki_spice_herb": 0,
        "katki_chocolate": 0,
        "katki_coffee": 0,
        "katki_chile": 0,
        "katki_smoke": 0,
        "katki_honey": 0,
        "katki_pumpkin": 0,
        "katki_salt": 0,
        "katki_lactose": 0,
        "mash_temp_c": 66,
        "fermentation_temp_c": 19,
        "yeast_attenuation": 78,
        "boil_time_min": 60,
        "water_ca_ppm": 150,
        "water_so4_ppm": 250,
        "water_cl_ppm": 120,
        "dry_hop_days": 0,
        "mash_type_step": 0,
        "mash_type_decoction": 0,
        "lagering_days": 0
      },
      "in_split": null
    }
  ]
}