{
  "meta": {
    "sprint": "Adim 18c-1c-5d V28b C3 belle saison dogrulama",
    "rule_refs": [
      "KURAL 1.4 (recete vs flag)",
      "KURAL 4.4 (oneri yasagi)",
      "KURAL 6.3 (sample N=10)"
    ],
    "sha256_check": {
      "v27_pre": "8c2d132d1913a57203040a98c9ef1ceebc2e18ce771b0f233718e1215c12442d",
      "v27_post": "8c2d132d1913a57203040a98c9ef1ceebc2e18ce771b0f233718e1215c12442d",
      "v27_intact": true,
      "v28b_pre": "bc8a7b0dd900019ff79900e9f871641bfe162d1c41bbd85cb7f2f37a4b938024",
      "v28b_post": "bc8a7b0dd900019ff79900e9f871641bfe162d1c41bbd85cb7f2f37a4b938024",
      "v28b_intact": true
    }
  },
  "sample_count": 10,
  "samples": [
    {
      "id": "mmum_1108",
      "raw_yeast": "Belle Saison",
      "sadece_belle_saison": true,
      "ek_belgian_mayasi": false,
      "bjcp_slug": "french_belgian_saison",
      "slug_kategorisi": "saison",
      "yeast_saison_v27": 1,
      "yeast_saison_v28b": 1,
      "yeast_belgian_v27": 1,
      "yeast_belgian_v28b": 0
    },
    {
      "id": "mmum_1418",
      "raw_yeast": "Belle Saison",
      "sadece_belle_saison": true,
      "ek_belgian_mayasi": false,
      "bjcp_slug": "french_belgian_saison",
      "slug_kategorisi": "saison",
      "yeast_saison_v27": 1,
      "yeast_saison_v28b": 1,
      "yeast_belgian_v27": 1,
      "yeast_belgian_v28b": 0
    },
    {
      "id": "mmum_1499",
      "raw_yeast": "Belle Saison",
      "sadece_belle_saison": true,
      "ek_belgian_mayasi": false,
      "bjcp_slug": "french_belgian_saison",
      "slug_kategorisi": "saison",
      "yeast_saison_v27": 1,
      "yeast_saison_v28b": 1,
      "yeast_belgian_v27": 1,
      "yeast_belgian_v28b": 0
    },
    {
      "id": "mmum_1659",
      "raw_yeast": "Kveik Voss + Belle Saison",
      "sadece_belle_saison": true,
      "ek_belgian_mayasi": false,
      "bjcp_slug": "french_belgian_saison",
      "slug_kategorisi": "saison",
      "yeast_saison_v27": 1,
      "yeast_saison_v28b": 1,
      "yeast_belgian_v27": 1,
      "yeast_belgian_v28b": 0
    },
    {
      "id": "mmum_1733",
      "raw_yeast": "Belle Saison",
      "sadece_belle_saison": true,
      "ek_belgian_mayasi": false,
      "bjcp_slug": "french_belgian_saison",
      "slug_kategorisi": "saison",
      "yeast_saison_v27": 1,
      "yeast_saison_v28b": 1,
      "yeast_belgian_v27": 1,
      "yeast_belgian_v28b": 0
    },
    {
      "id": "mmum_1757",
      "raw_yeast": "LALLEMAND Belle Saison",
      "sadece_belle_saison": true,
      "ek_belgian_mayasi": false,
      "bjcp_slug": "french_belgian_saison",
      "slug_kategorisi": "saison",
      "yeast_saison_v27": 1,
      "yeast_saison_v28b": 1,
      "yeast_belgian_v27": 1,
      "yeast_belgian_v28b": 0
    },
    {
      "id": "mmum_1781",
      "raw_yeast": "LalBrew Belle Saison + Craft Series M31 Belgian Tripel",
      "sadece_belle_saison": false,
      "ek_belgian_mayasi": true,
      "bjcp_slug": "french_belgian_saison",
      "slug_kategorisi": "saison",
      "yeast_saison_v27": 1,
      "yeast_saison_v28b": 1,
      "yeast_belgian_v27": 1,
      "yeast_belgian_v28b": 0
    },
    {
      "id": "mmum_436",
      "raw_yeast": "Danstar Belle Saison",
      "sadece_belle_saison": true,
      "ek_belgian_mayasi": false,
      "bjcp_slug": "german_doppelbock",
      "slug_kategorisi": "diger",
      "yeast_saison_v27": 1,
      "yeast_saison_v28b": 1,
      "yeast_belgian_v27": 1,
      "yeast_belgian_v28b": 0
    },
    {
      "id": "mmum_517",
      "raw_yeast": "Danstar Belle Saison",
      "sadece_belle_saison": true,
      "ek_belgian_mayasi": false,
      "bjcp_slug": "french_belgian_saison",
      "slug_kategorisi": "saison",
      "yeast_saison_v27": 1,
      "yeast_saison_v28b": 1,
      "yeast_belgian_v27": 1,
      "yeast_belgian_v28b": 0
    },
    {
      "id": "mmum_567",
      "raw_yeast": "Danstar Belle Saison",
      "sadece_belle_saison": true,
      "ek_belgian_mayasi": false,
      "bjcp_slug": "french_belgian_saison",
      "slug_kategorisi": "saison",
      "yeast_saison_v27": 1,
      "yeast_saison_v28b": 1,
      "yeast_belgian_v27": 1,
      "yeast_belgian_v28b": 0
    }
  ],
  "ozet": {
    "sadece_belle_saison_count": 9,
    "ek_belgian_mayasi_count": 1,
    "yeast_saison_v27_eq_v28b_korundu_count": 10,
    "slug_saison_count": 9,
    "slug_belgian_count": 0,
    "slug_diger_count": 1
  }
}